flexpasm/__init__.py
flexpasm/backup.py
flexpasm/base.py
flexpasm/builder/__init__.py
flexpasm/builder/builder.py
flexpasm/builder/toolchain.py
flexpasm/constants.py
flexpasm/exceptions.py
flexpasm/instructions/registers.py
flexpasm/instructions/segments.py
flexpasm/instructions/syscalls.py
flexpasm/macros.py
flexpasm/mnemonics/__init__.py
flexpasm/mnemonics/arithmetic.py
flexpasm/mnemonics/base.py
flexpasm/mnemonics/bitshift.py
flexpasm/mnemonics/data.py
flexpasm/mnemonics/flow.py
flexpasm/mnemonics/io.py
flexpasm/mnemonics/logical.py
flexpasm/program.py
flexpasm/rich_highlighter.py
flexpasm/settings.py
flexpasm/templates.py
flexpasm/utils.py
flexpasm-0.3.2.dist-info/LICENSE
flexpasm-0.3.2.dist-info/METADATA
flexpasm-0.3.2.dist-info/WHEEL
flexpasm-0.3.2.dist-info/RECORD
