Metadata-Version: 2.3
Name: flexpasm
Version: 0.3.2
Summary: Python library for writing assembly code through object abstractions
License: MIT
Author: alexeev-prog
Author-email: alexeev.dev@mail.ru
Requires-Python: >=3.10,<4.0
Classifier: License :: OSI Approved :: MIT License
Classifier: Programming Language :: Python :: 3
Classifier: Programming Language :: Python :: 3.10
Classifier: Programming Language :: Python :: 3.11
Classifier: Programming Language :: Python :: 3.12
Classifier: Programming Language :: Python :: 3.13
Requires-Dist: rich (>=13.9.4,<14.0.0)
